{
  "updated_at_kst": "2026-06-02 06:15:12 KST",
  "updated_at_iso": "2026-06-02T06:15:12.200451+09:00",
  "codex_batches": [],
  "firestore": {
    "status": {
      "analyzed": 626272,
      "pending": 10756,
      "queued_codex": 0,
      "metadata": 19038,
      "skipped": 760,
      "failed": 54,
      "summarizing": 0
    },
    "categorySource": {
      "retag-flash": 212620,
      "mlx-v53": 11474,
      "mlx-v52": 0
    },
    "reviewNeeded": 41546
  },
  "daily_runs": [],
  "system": {
    "disk": {
      "total": "228Gi",
      "used": "17Gi",
      "avail": "67Gi",
      "pct": "20%"
    },
    "mlx_lm_running": true,
    "uvicorn_running": true
  }
}