{
  "updated_at_kst": "2026-06-23 12:24:52 KST",
  "updated_at_iso": "2026-06-23T12:24:52.062756+09:00",
  "codex_batches": [],
  "firestore": {
    "status": {
      "analyzed": 684057,
      "pending": 354,
      "queued_codex": 0,
      "metadata": 255216,
      "skipped": 1226,
      "failed": 0,
      "summarizing": 0
    },
    "categorySource": {
      "retag-flash": 212620,
      "mlx-v53": 25534,
      "mlx-v52": 0
    },
    "reviewNeeded": 46511
  },
  "daily_runs": [],
  "system": {
    "disk": {
      "total": "228Gi",
      "used": "17Gi",
      "avail": "45Gi",
      "pct": "27%"
    },
    "mlx_lm_running": true,
    "uvicorn_running": true
  }
}